chatmemoryc/__init__.py
chatmemoryc/__main__.py
chatmemoryc/chatmemoryc.py
chatmemoryc/client.py
chatmemoryc/server.py
chatmemoryc-0.1.4rc5.dist-info/LICENSE.txt
chatmemoryc-0.1.4rc5.dist-info/METADATA
chatmemoryc-0.1.4rc5.dist-info/WHEEL
chatmemoryc-0.1.4rc5.dist-info/top_level.txt
chatmemoryc-0.1.4rc5.dist-info/RECORD
