Metadata-Version: 2.1
Name: chatmemoryc
Version: 0.1.4rc5
Summary: Long-term and medium-term memories between you and chatbot
Home-page: https://github.com/f6844710/chatmemoryc
Author: pino
Author-email: f6844710@nifty.com
Maintainer: pino
Maintainer-email: f6844710@nifty.com
License: Apache v2
Classifier: Programming Language :: Python :: 3
License-File: LICENSE.txt
Requires-Dist: fastapi (==0.110.0)
Requires-Dist: anthropic (==0.28.0)
Requires-Dist: requests (==2.31.0)
Requires-Dist: SQLAlchemy (==2.0.28)
Requires-Dist: uvicorn (==0.28.1)
Requires-Dist: pycryptodome (==3.20.0)
